logging_toolbox/__init__.py
logging_toolbox/startup.py
logging_toolbox/utils.py
logging_toolbox/version.py
logging_toolbox/tests/__init__.py
logging_toolbox/tests/test_startup_log.py
logging_toolbox/tests/test_url_cleaner.py
logging_toolbox-0.2.0.dist-info/AUTHORS
logging_toolbox-0.2.0.dist-info/LICENSE
logging_toolbox-0.2.0.dist-info/METADATA
logging_toolbox-0.2.0.dist-info/WHEEL
logging_toolbox-0.2.0.dist-info/top_level.txt
logging_toolbox-0.2.0.dist-info/RECORD
