Metadata-Version: 2.1
Name: logging-toolbox
Version: 0.2.0
Summary: logging-toolbox
Home-page: https://github.com/thinnect/logging-toolbox
Author: Kaarel Ratas
Author-email: kaarel@thinnect.com
License: MIT
Platform: UNKNOWN
Classifier: Development Status :: 4 - Beta
Classifier: Intended Audience :: Developers
Classifier: License :: OSI Approved :: MIT License
Classifier: Programming Language :: Python :: 2
Classifier: Programming Language :: Python :: 3
Classifier: Topic :: System :: Logging
Classifier: Topic :: Utilities
Requires-Dist: six
